motiffinder/__init__.py
motiffinder/__main__.py
motiffinder/_version.py
motiffinder/mf_generate.py
motiffinder/mf_main.py
motiffinder/mf_query.py
motiffinder/mf_utils.py
motiffinder/static/__init__.py
motiffinder/static/blosum.json
motiffinder/static/flex.json
motiffinder-0.0.2.dist-info/LICENSE
motiffinder-0.0.2.dist-info/METADATA
motiffinder-0.0.2.dist-info/WHEEL
motiffinder-0.0.2.dist-info/entry_points.txt
motiffinder-0.0.2.dist-info/top_level.txt
motiffinder-0.0.2.dist-info/zip-safe
motiffinder-0.0.2.dist-info/RECORD
